observo/__init__.py
observo/templates/404.html
observo/templates/file_detail.html
observo/templates/index.html
observo/templates/login.html
observo-0.1.13.dist-info/METADATA
observo-0.1.13.dist-info/WHEEL
observo-0.1.13.dist-info/RECORD
