Metadata-Version: 2.3
Name: observo
Version: 0.1.13
Summary: Add your description here
Author: Renan Moretto
Author-email: renan_moretto@outlook.com
Requires-Python: >=3.10
Classifier: Programming Language :: Python :: 3
Classifier: Programming Language :: Python :: 3.10
Classifier: Programming Language :: Python :: 3.11
Classifier: Programming Language :: Python :: 3.12
Classifier: Programming Language :: Python :: 3.13
Requires-Dist: asgiref (>=3.8.0)
Requires-Dist: flask (>=3.0.0)
